scrapy_selenium_grid/README.rst
scrapy_selenium_grid/__init__.py
scrapy_selenium_grid/download_handler.py
scrapy_selenium_grid/mobile.py
scrapy_selenium_grid/shadowroot.py
scrapy_selenium_grid/switch_to.py
scrapy_selenium_grid/webdriver.py
scrapy_selenium_grid/webelement.py
scrapy_selenium_grid/common/__init__.py
scrapy_selenium_grid/common/action_chains.py
scrapy_selenium_grid/common/alert.py
scrapy_selenium_grid/common/actions/__init__.py
scrapy_selenium_grid/common/actions/action_builder.py
scrapy_selenium_grid/remote_connection/__init__.py
scrapy_selenium_grid/remote_connection/base.py
scrapy_selenium_grid/remote_connection/chrome.py
scrapy_selenium_grid/remote_connection/chromium.py
scrapy_selenium_grid/remote_connection/edge.py
scrapy_selenium_grid/remote_connection/firefox.py
scrapy_selenium_grid/remote_connection/safari.py
scrapy_selenium_grid/support/__init__.py
scrapy_selenium_grid/support/expected_conditions.py
scrapy_selenium_grid/support/select.py
scrapy_selenium_grid/support/wait.py
scrapy_selenium_grid-0.0.1.dist-info/LICENSE
scrapy_selenium_grid-0.0.1.dist-info/METADATA
scrapy_selenium_grid-0.0.1.dist-info/WHEEL
scrapy_selenium_grid-0.0.1.dist-info/top_level.txt
scrapy_selenium_grid-0.0.1.dist-info/RECORD
