Metadata-Version: 2.1
Name: scrapy-selenium-grid
Version: 0.0.1
Summary: Unofficial scrapy plugin for Selenium Grid
Home-page: https://github.com/dozymoe/scrapy-selenium-grid
Author: Fahri Reza
Author-email: dozymoe@gmail.com
License: BSD
Project-URL: Bug Tracker, https://github.com/dozymoe/scrapy-selenium-grid/issues
Classifier: Intended Audience :: Developers
Classifier: Operating System :: OS Independent
Classifier: Programming Language :: Python
Classifier: Programming Language :: Python :: 3
License-File: LICENSE
Requires-Dist: aiohttp
Requires-Dist: aiohttp-socks
Requires-Dist: scrapy
Requires-Dist: yarl
